pytouch/__init__.py
pytouch/base.py
pytouch/common/__init__.py
pytouch/common/constants.py
pytouch/common/visualizer.py
pytouch/datasets/__init__.py
pytouch/datasets/digit.py
pytouch/datasets/sensors.py
pytouch/datasets/sequence.py
pytouch/datasets/slip_sequence.py
pytouch/handlers/__init__.py
pytouch/handlers/image.py
pytouch/handlers/sensor.py
pytouch/handlers/video.py
pytouch/models/__init__.py
pytouch/models/slip_detect.py
pytouch/models/slip_resnet.py
pytouch/models/touch_detect.py
pytouch/models/zoo.py
pytouch/models/pix2pix/__init__.py
pytouch/models/pix2pix/pix2pix.py
pytouch/models/pix2pix/thirdparty/__init__.py
pytouch/models/pix2pix/thirdparty/poisson.py
pytouch/models/pix2pix/thirdparty/pix2pix/__init__.py
pytouch/models/pix2pix/thirdparty/pix2pix/data/__init__.py
pytouch/models/pix2pix/thirdparty/pix2pix/data/base_dataset.py
pytouch/models/pix2pix/thirdparty/pix2pix/models/__init__.py
pytouch/models/pix2pix/thirdparty/pix2pix/models/base_model.py
pytouch/models/pix2pix/thirdparty/pix2pix/models/networks.py
pytouch/models/pix2pix/thirdparty/pix2pix/models/pix2pix_model.py
pytouch/models/pix2pix/thirdparty/pix2pix/util/__init__.py
pytouch/models/pix2pix/thirdparty/pix2pix/util/util.py
pytouch/sensors/__init__.py
pytouch/sensors/base.py
pytouch/sensors/digit.py
pytouch/sensors/gelsight.py
pytouch/sensors/omnitact.py
pytouch/tasks/__init__.py
pytouch/tasks/contact_area.py
pytouch/tasks/slip_detect.py
pytouch/tasks/surface_3d.py
pytouch/tasks/touch_detect.py
pytouch/tasks/surface3d/__init__.py
pytouch/tasks/surface3d/geometry.py
pytouch/utils/__init__.py
pytouch/utils/common_utils.py
pytouch/utils/data_utils.py
pytouch/utils/model_utils.py
pytouch/utils/train_utils.py
pytouch/utils/transforms.py
pytouch/utils/vis_utils.py
train/__init__.py
train/train.py
train/datamodules/__init__.py
train/datamodules/slip_detect.py
train/datamodules/touch_detect.py
train/models/__init__.py
train/models/slip_detect.py
train/models/slip_resnet.py
train/models/touch_detect.py
pytouch-0.4.2.dist-info/AUTHORS.md
pytouch-0.4.2.dist-info/LICENSE
pytouch-0.4.2.dist-info/METADATA
pytouch-0.4.2.dist-info/WHEEL
pytouch-0.4.2.dist-info/top_level.txt
pytouch-0.4.2.dist-info/zip-safe
pytouch-0.4.2.dist-info/RECORD
