Metadata-Version: 2.1
Name: pytouch
Version: 0.4.2
Summary: A PyTorch library for tactile touch sensing.
Home-page: https://github.com/facebookresearch/pytouch
Author: Mike Lambeta, Roberto Calandra
Author-email: lambetam@fb.com, rcalandra@fb.com
License: LICENSE
Keywords: science
Platform: UNKNOWN
Classifier: Programming Language :: Python :: 3
Classifier: Operating System :: POSIX :: Linux
License-File: LICENSE
License-File: AUTHORS.md
Requires-Dist: black
Requires-Dist: flake8
Requires-Dist: flake8-copyright
Requires-Dist: isort
Requires-Dist: matplotlib (>=3.2.1)
Requires-Dist: nox (>=2019.11.9)
Requires-Dist: numpy (>=1.20.0)
Requires-Dist: torch (>=1.4.0)
Requires-Dist: torchvision (>=0.5.0)
Requires-Dist: pytorch3d
Requires-Dist: pytorch-lightning
Requires-Dist: hydra-core (>=1.0.3)
Requires-Dist: omegaconf (>=2.0.2)
Requires-Dist: pandas (>=1.0.3)
Requires-Dist: torchmetrics
Requires-Dist: opencv-python
Requires-Dist: boto3
Requires-Dist: onnx
Requires-Dist: onnxruntime
Requires-Dist: attrdict
Requires-Dist: open3d
Requires-Dist: scipy
